graphql_dsl/__init__.py
graphql_dsl/dsl.py
graphql_dsl/info.py
graphql_dsl/translator.py
graphql_dsl/types.py
graphql_dsl/cli/__init__.py
graphql_dsl/cli/gen.py
graphql_dsl/parser/__init__.py
graphql_dsl-0.2.1.dist-info/LICENSE
graphql_dsl-0.2.1.dist-info/METADATA
graphql_dsl-0.2.1.dist-info/WHEEL
graphql_dsl-0.2.1.dist-info/entry_points.txt
graphql_dsl-0.2.1.dist-info/top_level.txt
graphql_dsl-0.2.1.dist-info/RECORD
