Metadata-Version: 2.1
Name: graphql-dsl
Version: 0.2.1
Summary: Compose GraphQL queries by composing Python types!
Home-page: https://maximavanov.com/
Author: Maxim Avanov
Author-email: maxim.avanov@gmail.com
License: UNKNOWN
Project-URL: Documentation, https://graphql-dsl.rtfd.io/
Project-URL: Source, https://github.com/avanov/graphql-dsl
Keywords: web
Platform: UNKNOWN
Classifier: Development Status :: 1 - Planning
Classifier: Intended Audience :: Developers
Classifier: License :: OSI Approved
Classifier: License :: OSI Approved :: MIT License
Classifier: Programming Language :: Python
Classifier: Programming Language :: Python :: 3
Classifier: Operating System :: POSIX
Classifier: Topic :: Internet :: WWW/HTTP
Classifier: Topic :: Software Development :: Libraries
Classifier: Topic :: Software Development :: Code Generators
Classifier: Typing :: Typed
Requires-Dist: typeit (>=3.9.1.8)
Requires-Dist: graphql-core (>=3)
Requires-Dist: infix (==1.2)
